nbenumerate/__init__.py
nbenumerate/main.py
nbenumerate/version.py
nbenumerate-0.2.1.dist-info/entry_points.txt
nbenumerate-0.2.1.dist-info/WHEEL
nbenumerate-0.2.1.dist-info/METADATA
nbenumerate-0.2.1.dist-info/RECORD
