Metadata-Version: 2.1
Name: nbenumerate
Version: 0.2.1
Summary: Automatically enumerate the markdown titles in jupyter notebooks
Author: An Hoang
Author-email: anhoang31415@gmail.com
Requires-Python: >=3.8.9,<4
Classifier: Programming Language :: Python :: 3
Classifier: Programming Language :: Python :: 3.10
Classifier: Programming Language :: Python :: 3.9
Requires-Dist: click (>=8.1.2)
Requires-Dist: nbformat (>=5.4.0,<6.0.0)
